reaf/__init__.py
reaf/common/clip_commands_processor.py
reaf/common/concatenate_features_producer.py
reaf/common/crop_image_features_producer.py
reaf/common/delta_to_absolute_commands_processor.py
reaf/common/environment_reset_from_callable.py
reaf/common/external_signal_sparse_reward_provider.py
reaf/common/external_signal_termination_checker.py
reaf/common/flatten_features_producer.py
reaf/common/map_utils.py
reaf/common/maximum_steps_termination_checker.py
reaf/common/maximum_wall_clock_time_termination_checker.py
reaf/common/moving_average_filter_commands_processor.py
reaf/common/out_of_bounds_termination_checker.py
reaf/common/partitioner_action_space_adapter.py
reaf/common/position_to_velocity_commands_processor.py
reaf/common/relative_clip_commands_processor.py
reaf/common/rotation_matrix_to_quaternion_feature_producer.py
reaf/common/sequential_end_of_episode_handler.py
reaf/common/sequential_environment_reset.py
reaf/common/stack_features_producer.py
reaf/common/time_trigger.py
reaf/common/timestamp_features_producer.py
reaf/common/workspace_limits_termination_checker.py
reaf/common/time_trigger_deps/clock.cc
reaf/common/time_trigger_deps/clock.h
reaf/common/time_trigger_deps/cycle_timer.cc
reaf/common/time_trigger_deps/cycle_timer.h
reaf/common/time_trigger_deps/python/cycle_timer.cc
reaf/common/time_trigger_deps/python/cycle_timer.cpython-311-x86_64-linux-gnu.so
reaf/common/time_trigger_deps/python/cycle_timer.pyi
reaf/core/action_space_adapter.py
reaf/core/commands_processor.py
reaf/core/data_acquisition_and_control_layer.py
reaf/core/default_discount_provider.py
reaf/core/default_observation_space_adapter.py
reaf/core/device.py
reaf/core/device_coordinator.py
reaf/core/discount_provider.py
reaf/core/environment.py
reaf/core/features_observer.py
reaf/core/features_producer.py
reaf/core/logger.py
reaf/core/numpy_mock_assertions.py
reaf/core/observation_space_adapter.py
reaf-1.0.0.dist-info/METADATA
reaf-1.0.0.dist-info/WHEEL
reaf-1.0.0.dist-info/RECORD
reaf-1.0.0.dist-info/licenses/LICENSE
