Metadata-Version: 2.4
Name: reaf
Version: 1.0.0
Summary: Robotics Environment Authoring Framework.
Keywords: RL,Reinforcement Learning,AI,ML,Environment,Authoring tool
Author-Email: Google DeepMind <robotics+oss@google.com>
Maintainer-Email: Antoine Laurens <alaurens@google.com>, Francesco Romano <fraromano@google.com>, Jose Enrique Chen <josechenf@google.com>
License-Expression: Apache-2.0
License-File: LICENSE
Classifier: Development Status :: 4 - Beta
Classifier: Intended Audience :: Science/Research
Classifier: Topic :: Scientific/Engineering :: Artificial Intelligence
Classifier: Typing :: Typed
Project-URL: Repository, https://github.com/google-deepmind/reaf.git
Project-URL: Issues, https://github.com/google-deepmind/reaf/issues
Requires-Python: >=3.10
Requires-Dist: numpy>=2
Requires-Dist: absl-py
Requires-Dist: dm-env
Requires-Dist: gdm_robotics
Requires-Dist: typing-extensions
Requires-Dist: immutabledict
Requires-Dist: pytest
Requires-Dist: StrEnum
Requires-Dist: scipy
